toggl/TogglPy.py
toggl/__init__.py
toggl/tests.py
toggl/toggl2gsuite.py
skip_TogglPy-0.2.0.dist-info/LICENSE
skip_TogglPy-0.2.0.dist-info/METADATA
skip_TogglPy-0.2.0.dist-info/WHEEL
skip_TogglPy-0.2.0.dist-info/top_level.txt
skip_TogglPy-0.2.0.dist-info/RECORD
